numpy_json/__init__.py
numpy_json/py.typed
numpy_json-0.1.0.dist-info/licenses/LICENSE
numpy_json-0.1.0.dist-info/METADATA
numpy_json-0.1.0.dist-info/WHEEL
numpy_json-0.1.0.dist-info/top_level.txt
numpy_json-0.1.0.dist-info/RECORD
