Metadata-Version: 2.4
Name: numpy-json
Version: 0.1.0
Summary: JSON encoder for NumPy arrays and extended Python data types
Home-page: https://github.com/featrix/numpy-json
Author: Featrix, Inc.
Author-email: "Featrix, Inc." <info@featrix.com>
Maintainer-email: "Featrix, Inc." <info@featrix.com>
License: MIT
Project-URL: Homepage, https://github.com/featrix/numpy-json
Project-URL: Documentation, https://github.com/featrix/numpy-json#readme
Project-URL: Repository, https://github.com/featrix/numpy-json
Project-URL: Bug Tracker, https://github.com/featrix/numpy-json/issues
Keywords: numpy,json,encoder,serialization,array,scientific computing,data science
Classifier: Development Status :: 4 - Beta
Classifier: Intended Audience :: Developers
Classifier: Intended Audience :: Science/Research
Classifier: License :: OSI Approved :: MIT License
Classifier: Operating System :: OS Independent
Classifier: Programming Language :: Python :: 3
Classifier: Programming Language :: Python :: 3.8
Classifier: Programming Language :: Python :: 3.9
Classifier: Programming Language :: Python :: 3.10
Classifier: Programming Language :: Python :: 3.11
Classifier: Programming Language :: Python :: 3.12
Classifier: Topic :: Scientific/Engineering
Classifier: Topic :: Software Development :: Libraries :: Python Modules
Classifier: Topic :: Utilities
Requires-Python: >=3.8
License-File: LICENSE
Requires-Dist: numpy>=1.20.0
Provides-Extra: dev
Requires-Dist: pytest>=7.0.0; extra == "dev"
Requires-Dist: pytest-cov>=4.0.0; extra == "dev"
Requires-Dist: black>=23.0.0; extra == "dev"
Requires-Dist: flake8>=6.0.0; extra == "dev"
Requires-Dist: mypy>=1.0.0; extra == "dev"
Requires-Dist: pandas>=1.3.0; extra == "dev"
Dynamic: author
Dynamic: home-page
Dynamic: license-file
Dynamic: requires-python
